geomltools/__init__.py
geomltools/datasets/__init__.py
geomltools/datasets/spatial_data.py
geomltools/datasets/data/Detroit 911 Calls.csv
geomltools/datasets/data/__init__.py
geomltools/datasets/data/earthquakes_2006_2019.csv
geomltools/spatial_statistics/__init__.py
geomltools/spatial_statistics/descriptive_statistics.py
geomltools/spatial_statistics/spatial_indices.py
geomltools/spatial_statistics/spatial_relationships.py
geomltools-0.2.7.dist-info/licenses/LICENSE
geomltools-0.2.7.dist-info/METADATA
geomltools-0.2.7.dist-info/WHEEL
geomltools-0.2.7.dist-info/top_level.txt
geomltools-0.2.7.dist-info/RECORD
