Metadata-Version: 2.4
Name: geomltools
Version: 0.2.7
Summary: A Python library for spatial machine learning and geospatial analysis.
Home-page: https://github.com/Fneich/geomltools
Author: Mohammad Ali Fneich
Author-email: fneichmohamad@gmail.com
Classifier: Programming Language :: Python :: 3
Classifier: License :: OSI Approved :: MIT License
Classifier: Operating System :: OS Independent
Requires-Python: >=3.6
License-File: LICENSE
Requires-Dist: numpy
Requires-Dist: pandas
Requires-Dist: scipy
Requires-Dist: geopandas
Requires-Dist: shapely
Requires-Dist: matplotlib
Requires-Dist: scikit-learn
Requires-Dist: arcgis
Dynamic: author
Dynamic: author-email
Dynamic: classifier
Dynamic: description
Dynamic: description-content-type
Dynamic: home-page
Dynamic: license-file
Dynamic: requires-dist
Dynamic: requires-python
Dynamic: summary
